{
  "openapi": "3.0.0",
  "info": {
    "title": "loki",
    "version": "0.0.0",
    "x-schema-identifier": "loki",
    "x-schema-kind": "composable",
    "x-schema-variant": "dataquery"
  },
  "paths": {},
  "components": {
    "schemas": {
      "QueryEditorMode": {
        "enum": [
          "code",
          "builder"
        ]
      },
      "LokiQueryType": {
        "enum": [
          "range",
          "instant",
          "stream"
        ]
      },
      "SupportingQueryType": {
        "enum": [
          "logsVolume",
          "logsSample",
          "dataSample",
          "infiniteScroll"
        ]
      },
      "LokiQueryDirection": {
        "enum": [
          "forward",
          "backward"
        ]
      },
      "dataquery": {
        "type": "object",
        "additionalProperties": false,
        "properties": {
          "expr": {
            "type": "string"
          },
          "legendFormat": {
            "type": "string"
          },
          "maxLines": {
            "type": "integer"
          },
          "resolution": {
            "type": "integer"
          },
          "editorMode": {
            "$ref": "#/components/schemas/QueryEditorMode"
          },
          "range": {
            "type": "boolean"
          },
          "instant": {
            "type": "boolean"
          },
          "step": {
            "type": "string"
          },
          "refId": {
            "type": "string"
          },
          "hide": {
            "type": "boolean"
          },
          "queryType": {
            "type": "string"
          },
          "datasource": {
            "type": "object",
            "additionalProperties": {}
          }
        }
      }
    }
  }
}